bella_companion/__init__.py
bella_companion/backend/__init__.py
bella_companion/backend/activation_functions.py
bella_companion/backend/mlp.py
bella_companion/backend/plots.py
bella_companion/backend/type_hints.py
bella_companion/backend/utils/__init__.py
bella_companion/backend/utils/beast.py
bella_companion/backend/utils/metrics.py
bella_companion/backend/utils/misc.py
bella_companion/backend/utils/slurm.py
bella_companion/backend/xAI/__init__.py
bella_companion/backend/xAI/pdp.py
bella_companion/backend/xAI/shapley.py
bella_companion/cli.py
bella_companion/eucovid/__init__.py
bella_companion/eucovid/beast_configs/BELLA.xml
bella_companion/eucovid/beast_configs/GLM.xml
bella_companion/eucovid/data/flights_and_populations/changetimes.csv
bella_companion/eucovid/data/flights_and_populations/flights.csv
bella_companion/eucovid/data/flights_and_populations/populations.csv
bella_companion/eucovid/data/flights_over_populations/changetimes.csv
bella_companion/eucovid/data/flights_over_populations/flights_over_populations.csv
bella_companion/eucovid/data/msa.fasta
bella_companion/eucovid/plot.py
bella_companion/eucovid/run.py
bella_companion/eucovid/settings.py
bella_companion/eucovid/summarize.py
bella_companion/platyrrhine/__init__.py
bella_companion/platyrrhine/beast_config.xml
bella_companion/platyrrhine/data/change_times.csv
bella_companion/platyrrhine/data/traits.csv
bella_companion/platyrrhine/data/trees.nwk
bella_companion/platyrrhine/plot.py
bella_companion/platyrrhine/run.py
bella_companion/platyrrhine/settings.py
bella_companion/platyrrhine/summarize.py
bella_companion/simulations/__init__.py
bella_companion/simulations/beast_configs/epi-multitype/BELLA.xml
bella_companion/simulations/beast_configs/epi-multitype/GLM.xml
bella_companion/simulations/beast_configs/epi-multitype/PA.xml
bella_companion/simulations/beast_configs/epi-skyline/BELLA.xml
bella_companion/simulations/beast_configs/epi-skyline/GLM.xml
bella_companion-0.1.20.dist-info/WHEEL
bella_companion-0.1.20.dist-info/entry_points.txt
bella_companion-0.1.20.dist-info/METADATA
bella_companion-0.1.20.dist-info/RECORD
