Metadata-Version: 2.3
Name: bella-companion
Version: 0.1.20
Summary: Bayesian Evolutionary Layered Learning Architectures (BELLA) companion
Author: gabriele-marino
Author-email: gabriele-marino <gabmarino.8601@gmail.com>
Requires-Dist: arviz==0.22.0
Requires-Dist: autoregistry>=1.2.0
Requires-Dist: dotenv>=0.9.9
Requires-Dist: phylogenie>=3.1.14
Requires-Dist: plotly>=6.5.0
Requires-Dist: scipy>=1.15.3
Requires-Dist: seaborn>=0.13.2
Requires-Dist: shap>=0.49.1
Requires-Python: >=3.10
